sigma/__init__.py
sigma/__main__.py
sigma/cli.py
sigma/errors.py
sigma/parser.py
supersigma2_errorcodes-1.2.dist-info/entry_points.txt
supersigma2_errorcodes-1.2.dist-info/LICENSE
supersigma2_errorcodes-1.2.dist-info/WHEEL
supersigma2_errorcodes-1.2.dist-info/METADATA
supersigma2_errorcodes-1.2.dist-info/RECORD
