Metadata-Version: 2.1
Name: supersigma2-errorcodes
Version: 1.2
Summary: A parser for DMC SuperSigma2 error codes
License: GPL-3.0-or-later
Author: Thomas Feldmann
Author-email: mail@tfeldmann.de
Requires-Python: >=3.6,<4.0
Classifier: License :: OSI Approved :: GNU General Public License v3 or later (GPLv3+)
Classifier: Programming Language :: Python :: 3
Classifier: Programming Language :: Python :: 3.6
Classifier: Programming Language :: Python :: 3.7
Classifier: Programming Language :: Python :: 3.8
Classifier: Programming Language :: Python :: 3.9
